setup.cfg
setup.py
larVolumeToObj/__init__.py
larVolumeToObj.egg-info/PKG-INFO
larVolumeToObj.egg-info/SOURCES.txt
larVolumeToObj.egg-info/dependency_links.txt
larVolumeToObj.egg-info/pbr.json
larVolumeToObj.egg-info/requires.txt
larVolumeToObj.egg-info/top_level.txt
larVolumeToObj/computation/__init__.py
larVolumeToObj/computation/calc_chains_helper.pyx
larVolumeToObj/computation/data_preparation.py
larVolumeToObj/computation/fileio.py
larVolumeToObj/computation/import_library.py
larVolumeToObj/computation/laplacianSmoothing.py
larVolumeToObj/computation/lar.py
larVolumeToObj/computation/matrixutil_accel.py
larVolumeToObj/computation/matrixutil_no_accel.py
larVolumeToObj/computation/objToVolume.py
larVolumeToObj/computation/pklzToSmoothObj.py
larVolumeToObj/computation/pngstack2array3d.py
larVolumeToObj/computation/smooth.py
larVolumeToObj/computation/step_calcchains_serial_tobinary_filter_proc.py
larVolumeToObj/computation/step_calcchains_serial_tobinary_filter_proc_lisa.py
larVolumeToObj/computation/step_generatebordermtx.py
larVolumeToObj/computation/step_loadmodel.py
larVolumeToObj/computation/step_mergemesh.py
larVolumeToObj/computation/step_remove_boxes_iner_faces.py
larVolumeToObj/computation/step_squaremesh.py
larVolumeToObj/computation/step_triangularmesh.py
larVolumeToObj/computation/visualization.py
larVolumeToObj/packages/__init__.py
larVolumeToObj/packages/check-packages.py