Metadata-Version: 1.1
Name: larVolumeToObj
Version: 1.0.25
Summary: 3D data read from pklz and write to obj
Home-page: https://github.com/mjirik/larVolumeToObj
Author: Miroslav Jirik, Francesco Furiani
Author-email: miroslav.jirik@gmail.com
License: MIT
Keywords: dicom 3D visualization
Platform: UNKNOWN
Classifier: Development Status :: 3 - Alpha
Classifier: Intended Audience :: Developers
Classifier: Topic :: Scientific/Engineering :: Bio-Informatics
Classifier: License :: OSI Approved :: BSD License
Classifier: Programming Language :: Python :: 2.7
